llama_index/agent/coa/__init__.py
llama_index/agent/coa/output_parser.py
llama_index/agent/coa/prompts.py
llama_index/agent/coa/step.py
llama_index/agent/coa/utils.py
llama_index_agent_coa-0.3.3.dist-info/METADATA
llama_index_agent_coa-0.3.3.dist-info/WHEEL
llama_index_agent_coa-0.3.3.dist-info/licenses/LICENSE
llama_index_agent_coa-0.3.3.dist-info/RECORD
