Metadata-Version: 2.4
Name: llama-index-agent-coa
Version: 0.3.3
Summary: llama-index agent coa integration
Author-email: Logan Markewich <logan@runllama.ai>
Maintainer: jerryjliu
License-Expression: MIT
License-File: LICENSE
Requires-Python: <4.0,>=3.9
Requires-Dist: llama-index-core<0.13,>=0.12.0
